Metadata-Version: 2.1
Name: digispark
Version: 0.1.0
Summary: ATtiny-85 Digispark module
Home-page: https://github.com/netgian/digispark
Author: Gian Glen
Author-email: gianlopez1605@gmail.com
License: GNU General Public License v3.0
Classifier: Development Status :: 1 - Planning
Classifier: Programming Language :: Python :: 3
